{"chunk_definitions":[{"row":72,"row_count":1,"visible":true,"expansion_state":0,"options":{"engine":"r","label":"unnamed-chunk-188","dev":"png"},"document_id":"21EEFD95","chunk_id":"c1sm3ybn93svv","chunk_label":"unnamed-chunk-1"},{"row":83,"row_count":1,"visible":true,"expansion_state":0,"options":{"engine":"r","label":"unnamed-chunk-189","dev":"png"},"document_id":"21EEFD95","chunk_id":"ciqhtmc5kxql3","chunk_label":"unnamed-chunk-2"},{"row":98,"row_count":1,"visible":true,"expansion_state":0,"options":{"engine":"r","label":"unnamed-chunk-190","dev":"png"},"document_id":"21EEFD95","chunk_id":"c3bw267655pes","chunk_label":"unnamed-chunk-3"},{"row":109,"row_count":1,"visible":true,"expansion_state":0,"options":{"engine":"r","label":"unnamed-chunk-191","dev":"png"},"document_id":"21EEFD95","chunk_id":"cbuqadluw4j2y","chunk_label":"unnamed-chunk-4"},{"row":121,"row_count":1,"visible":true,"expansion_state":0,"options":{"engine":"r","label":"unnamed-chunk-192","dev":"png"},"document_id":"21EEFD95","chunk_id":"cczub9g3umdrk","chunk_label":"unnamed-chunk-5"},{"row":141,"row_count":1,"visible":true,"expansion_state":0,"options":{"engine":"r","label":"unnamed-chunk-193","dev":"png"},"document_id":"21EEFD95","chunk_id":"cuq0yn8gvucc1","chunk_label":"unnamed-chunk-6"},{"row":154,"row_count":1,"visible":true,"expansion_state":0,"options":{"engine":"r","label":"unnamed-chunk-194","dev":"png"},"document_id":"21EEFD95","chunk_id":"c2m7fli5yf691","chunk_label":"unnamed-chunk-7"},{"row":166,"row_count":1,"visible":true,"expansion_state":0,"options":{"engine":"r","label":"unnamed-chunk-195","dev":"png"},"document_id":"21EEFD95","chunk_id":"c866jj4pmn2dr","chunk_label":"unnamed-chunk-8"},{"row":181,"row_count":1,"visible":true,"expansion_state":0,"options":{"engine":"r","label":"unnamed-chunk-196","dev":"png"},"document_id":"21EEFD95","chunk_id":"cjfve7ne97b1n","chunk_label":"unnamed-chunk-9"},{"row":194,"row_count":1,"visible":true,"expansion_state":0,"options":{"engine":"r","label":"unnamed-chunk-197","dev":"png"},"document_id":"21EEFD95","chunk_id":"cn0mfwdbu8cbj","chunk_label":"unnamed-chunk-10"},{"row":215,"row_count":1,"visible":true,"expansion_state":0,"options":{"engine":"r","label":"unnamed-chunk-217","dev":"png"},"document_id":"21EEFD95","chunk_id":"csttacgk6fmte","chunk_label":"unnamed-chunk-11"},{"row":237,"row_count":1,"visible":true,"expansion_state":0,"options":{"engine":"r","label":"unnamed-chunk-219","dev":"png"},"document_id":"21EEFD95","chunk_id":"cg6mzqet71tcq","chunk_label":"unnamed-chunk-12"},{"row":249,"row_count":1,"visible":true,"expansion_state":0,"options":{"engine":"r","label":"unnamed-chunk-3","dev":"png"},"document_id":"21EEFD95","chunk_id":"c6ik4b8ka9u7m","chunk_label":"unnamed-chunk-13"},{"row":261,"row_count":1,"visible":true,"expansion_state":0,"options":{"engine":"r","label":"unnamed-chunk-201","dev":"png"},"document_id":"21EEFD95","chunk_id":"cnewyd8ongysh","chunk_label":"unnamed-chunk-14"},{"row":276,"row_count":1,"visible":true,"expansion_state":0,"options":{"engine":"r","label":"unnamed-chunk-202","dev":"png"},"document_id":"21EEFD95","chunk_id":"cio25vvflkxfd","chunk_label":"unnamed-chunk-15"},{"row":322,"row_count":1,"visible":true,"expansion_state":0,"options":{"engine":"r","echo":false,"out.width":"70%","fig.align":"center","label":"unnamed-chunk-203","dev":"png"},"document_id":"21EEFD95","chunk_id":"ccsq82f60idba","chunk_label":"unnamed-chunk-16"},{"row":381,"row_count":1,"visible":true,"expansion_state":0,"options":{"engine":"r","label":"unnamed-chunk-234","dev":"png"},"document_id":"21EEFD95","chunk_id":"cekpc21u5vyhs","chunk_label":"unnamed-chunk-17"},{"row":390,"row_count":1,"visible":true,"expansion_state":0,"options":{"engine":"r","label":"unnamed-chunk-205","dev":"png"},"document_id":"21EEFD95","chunk_id":"c9xpa1qb1xxrd","chunk_label":"unnamed-chunk-18"},{"row":397,"row_count":1,"visible":true,"expansion_state":0,"options":{"engine":"r","label":"unnamed-chunk-206","dev":"png"},"document_id":"21EEFD95","chunk_id":"cy76dtg3ydq0v","chunk_label":"unnamed-chunk-19"},{"row":413,"row_count":1,"visible":true,"expansion_state":0,"options":{"engine":"r","label":"unnamed-chunk-207","dev":"png"},"document_id":"21EEFD95","chunk_id":"cg6kyqx8mysy5","chunk_label":"unnamed-chunk-20"},{"row":424,"row_count":1,"visible":true,"expansion_state":0,"options":{"engine":"r","label":"unnamed-chunk-208","dev":"png"},"document_id":"21EEFD95","chunk_id":"c0oop79vt3kt5","chunk_label":"unnamed-chunk-21"},{"row":441,"row_count":1,"visible":true,"expansion_state":0,"options":{"engine":"r","label":"unnamed-chunk-209","dev":"png"},"document_id":"21EEFD95","chunk_id":"czifo5pjiu9y4","chunk_label":"unnamed-chunk-22"},{"row":462,"row_count":1,"visible":true,"expansion_state":0,"options":{"engine":"r","label":"unnamed-chunk-233","dev":"png"},"document_id":"21EEFD95","chunk_id":"c27yrzvzpaiwl","chunk_label":"unnamed-chunk-23"}],"doc_write_time":1708892239}